ja_webutils/Page.py
ja_webutils/PageForm.py
ja_webutils/PageItem.py
ja_webutils/PageTable.py
ja_webutils/StringBuilder.py
ja_webutils/__init__.py
ja_webutils/_version.py
ja_webutils/webutilerror.py
ja_webutils-0.1.12.dist-info/licenses/LICENSE.txt
ja_webutils-0.1.12.dist-info/METADATA
ja_webutils-0.1.12.dist-info/WHEEL
ja_webutils-0.1.12.dist-info/top_level.txt
ja_webutils-0.1.12.dist-info/RECORD
