Metadata-Version: 2.4
Name: ja_webutils
Version: 0.1.12
Summary: A python package to support HTML generation
Author-email: Joseph Areeda <joseph.areeda@ligo.org>
License: GPL-3.0-or-later
Classifier: Development Status :: 4 - Beta
Classifier: Environment :: Web Environment
Classifier: Intended Audience :: Developers
Classifier: License :: OSI Approved :: GNU General Public License v3 or later (GPLv3+)
Classifier: Natural Language :: English
Classifier: Operating System :: OS Independent
Classifier: Programming Language :: Python
Classifier: Programming Language :: Python :: 3
Classifier: Programming Language :: Python :: 3.10
Classifier: Programming Language :: Python :: 3.11
Classifier: Topic :: Software Development :: Libraries
Requires-Python: >=3.10
License-File: LICENSE.txt
Provides-Extra: test
Requires-Dist: pytest>=3.9.1; extra == "test"
Dynamic: license-file
